checks_superstaq/__init__.py
checks_superstaq/_version.py
checks_superstaq/all_.py
checks_superstaq/build_docs.py
checks_superstaq/check_utils.py
checks_superstaq/checks-pyproject.toml
checks_superstaq/configs.py
checks_superstaq/coverage_.py
checks_superstaq/format_.py
checks_superstaq/licenses.py
checks_superstaq/lint_.py
checks_superstaq/mypy_.py
checks_superstaq/py.typed
checks_superstaq/pytest_.py
checks_superstaq/requirements.py
checks_superstaq-0.5.61.dist-info/METADATA
checks_superstaq-0.5.61.dist-info/WHEEL
checks_superstaq-0.5.61.dist-info/top_level.txt
checks_superstaq-0.5.61.dist-info/RECORD
