Metadata-Version: 2.4
Name: checks-superstaq
Version: 0.5.61
Summary: Check script tools for Superstaq.
Author-email: Superstaq development team <superstaq@infleqtion.com>
License: Apache-2.0
Project-URL: homepage, https://github.com/Infleqtion/client-superstaq
Requires-Python: >=3.9.0
Requires-Dist: coverage[toml]>=7.10.6
Requires-Dist: ipywidgets>=8.0.0
Requires-Dist: licensepy>=1.1.2
Requires-Dist: mypy>=1.7.0
Requires-Dist: nbmake>=1.3.0
Requires-Dist: nbsphinx>=0.9.0
Requires-Dist: pandoc>=2.3
Requires-Dist: pydantic>=1.10.7
Requires-Dist: pytest>=6.2.5
Requires-Dist: pytest-randomly>=3.10.1
Requires-Dist: pytest-socket>=0.7.0
Requires-Dist: pytest-xdist>=3.4.0
Requires-Dist: ruff>=0.13.0
Requires-Dist: setuptools>=67.0.0
Requires-Dist: sphinx-autoapi>=3.2.1
Requires-Dist: sphinx-rtd-theme>=1.0.0
